datapipe_label_studio_lite/__init__.py
datapipe_label_studio_lite/pipeline.py
datapipe_label_studio_lite/sdk_utils.py
datapipe_label_studio_lite-0.3.5.dist-info/METADATA
datapipe_label_studio_lite-0.3.5.dist-info/WHEEL
datapipe_label_studio_lite-0.3.5.dist-info/RECORD
